normal_form/__init__.py
normal_form/cnf.py
normal_form/cnf_simplify.py
normal_form/prop.py
normal_form/py.typed
normal_form/sat.py
normal_form/sxpr.py
normal_form/tests/__init__.py
normal_form/tests/test_cnf.py
normal_form/tests/test_cnf_simplify.py
normal_form/tests/test_normal_form.py
normal_form/tests/test_prop.py
normal_form/tests/test_sat.py
normal_form/tests/test_sxpr.py
normal_form-0.1.7.dist-info/LICENSE
normal_form-0.1.7.dist-info/WHEEL
normal_form-0.1.7.dist-info/METADATA
normal_form-0.1.7.dist-info/RECORD
