Metadata-Version: 2.1
Name: normal-form
Version: 0.1.7
Summary: A Python package for working with Conjunctive Normal Form (CNFs) and Boolean Satisfiability
Home-page: https://vaibhavkarve.github.io/normal-form/
License: GPL-3.0-or-later
Keywords: cnf,typed,logic,python3,sat-solver,sat,clause
Author: Vaibhav Karve
Author-email: vkarve@protonmail.com
Requires-Python: >=3.10,<4.0
Classifier: Development Status :: 4 - Beta
Classifier: Intended Audience :: Science/Research
Classifier: License :: OSI Approved :: GNU General Public License v3 or later (GPLv3+)
Classifier: Natural Language :: English
Classifier: Operating System :: OS Independent
Classifier: Programming Language :: Python :: 3
Classifier: Programming Language :: Python :: 3.10
Classifier: Programming Language :: Python :: 3.10
Classifier: Topic :: Scientific/Engineering :: Mathematics
Classifier: Typing :: Typed
Requires-Dist: colorama (>=0.4.5,<0.5.0)
Requires-Dist: loguru (>=0.6.0,<0.7.0)
Requires-Dist: more-itertools (>=8.14.0,<9.0.0)
Requires-Dist: python-sat[aiger,pblib] (>=0.1.7-dev.15,<0.2.0)
Requires-Dist: tqdm (>=4.64.0,<5.0.0)
Requires-Dist: typing-extensions (>=4.3.0,<5.0.0)
Project-URL: Documentation, https://vaibhavkarve.github.io/normal-form/
Project-URL: Repository, https://github.com/vaibhavkarve/normal-form
